accurate_benchmark/__init__.py
accurate_benchmark/benchmarking.py
accurate_benchmark/parameters.py
accurate_benchmark-2.3.0.dist-info/licenses/LICENSE.md
accurate_benchmark-2.3.0.dist-info/METADATA
accurate_benchmark-2.3.0.dist-info/WHEEL
accurate_benchmark-2.3.0.dist-info/top_level.txt
accurate_benchmark-2.3.0.dist-info/RECORD
