Metadata-Version: 2.4
Name: accurate-benchmark
Version: 2.3.0
Summary: A python package for accurate benchmarking and speed comparisons
Author: JetVolcano
Maintainer: JetVolcano
License: # MIT License
Project-URL: Source, https://github.com/JetVolcano/accurate-benchmar
Project-URL: Issues, https://github.com/JetVolcano/accurate-benchmark/issues
Requires-Python: >=3.13
License-File: LICENSE.md
Requires-Dist: numpy>=2.3.2
Requires-Dist: scipy>=1.16.0
Dynamic: license-file
